rafter/__init__.py
rafter/app.py
rafter/blueprints.py
rafter/exceptions.py
rafter/filters.py
rafter/http.py
rafter/contrib/__init__.py
rafter/contrib/schematics/__init__.py
rafter/contrib/schematics/app.py
rafter/contrib/schematics/exceptions.py
rafter/contrib/schematics/filters.py
rafter/contrib/schematics/helpers.py
rafter-1.2.0.dist-info/DESCRIPTION.rst
rafter-1.2.0.dist-info/METADATA
rafter-1.2.0.dist-info/RECORD
rafter-1.2.0.dist-info/WHEEL
rafter-1.2.0.dist-info/metadata.json
rafter-1.2.0.dist-info/top_level.txt
rafter-1.2.0.dist-info/zip-safe
